smbjoin/__init__.py
smbjoin/__main__.py
smbjoin/cli.py
smbjoin/crypt.py
smbjoin/lib.py
smbjoin/reg.py
smbjoin/util.py
smbjoin-0.1.1.dist-info/LICENSE
smbjoin-0.1.1.dist-info/METADATA
smbjoin-0.1.1.dist-info/WHEEL
smbjoin-0.1.1.dist-info/entry_points.txt
smbjoin-0.1.1.dist-info/top_level.txt
smbjoin-0.1.1.dist-info/zip-safe
smbjoin-0.1.1.dist-info/RECORD
