Metadata-Version: 2.1
Name: smbjoin
Version: 0.1.1
Summary: Offline Windows AD domain join tool for Samba
Home-page: https://github.com/ravenexp/smbjoin
Author: Sergey Kvachonok
Author-email: ravenexp@gmail.com
License: MIT
Keywords: ADS,Samba,TDB,Windows
Platform: UNKNOWN
Requires-Python: >=3.6
License-File: LICENSE
Requires-Dist: pycryptodome (~=3.10.0)
Requires-Dist: regipy (~=2.2.0)
